Chexpert_Classifier/__init__.py
Chexpert_Classifier/main.py
ChexpertClassifier-0.0.1.dist-info/METADATA
ChexpertClassifier-0.0.1.dist-info/WHEEL
ChexpertClassifier-0.0.1.dist-info/top_level.txt
ChexpertClassifier-0.0.1.dist-info/RECORD
