Metadata-Version: 2.1
Name: ChexpertClassifier
Version: 0.0.1
Summary: CheXpert Classification with EfficientNet B3
Home-page: UNKNOWN
Author: Mehdi Hosseini Moghadam
Author-email: <m.h.moghadam1996@gmail.com>
License: UNKNOWN
Keywords: Chexpert,Chest X-ray,X-ray image classification,Image classification,Computer Vision,EfficientNet,EfficientNet B3,Biomedical image classificationChest X-ray image classification
Platform: UNKNOWN
Classifier: Development Status :: 1 - Planning
Classifier: Intended Audience :: Developers
Classifier: Programming Language :: Python :: 3
Classifier: Operating System :: Unix
Classifier: Operating System :: MacOS :: MacOS X
Classifier: Operating System :: Microsoft :: Windows
Requires-Dist: pandas
Requires-Dist: numpy
Requires-Dist: opencv-python
Requires-Dist: torch
Requires-Dist: torchvision
Requires-Dist: tqdm
Requires-Dist: sklearn
